heic2png/__init__.py
heic2png/cli.py
heic2png/heic2png.py
heic2png-1.2.0.dist-info/licenses/LICENSE
heic2png-1.2.0.dist-info/METADATA
heic2png-1.2.0.dist-info/WHEEL
heic2png-1.2.0.dist-info/entry_points.txt
heic2png-1.2.0.dist-info/top_level.txt
heic2png-1.2.0.dist-info/RECORD
