Metadata-Version: 2.4
Name: HEIC2PNG
Version: 1.2.0
Summary: Convert format of HEIC image to PNG by using Python.
Home-page: https://github.com/natlee/HEIC2PNG
Author: Nat Lee
Author-email: natlee.work@gmail.com
Project-URL: Documentation, https://github.com/natlee/HEIC2PNG
Project-URL: Bug Reports, https://github.com/natlee/HEIC2PNG/issues
Project-URL: Source Code, https://github.com/natlee/HEIC2PNG
Keywords: HEIC,PNG,converter,image
Classifier: Development Status :: 5 - Production/Stable
Classifier: Intended Audience :: Developers
Classifier: Topic :: Software Development :: Build Tools
Classifier: Programming Language :: Python :: 3
Classifier: Programming Language :: Python :: 3.8
Classifier: Programming Language :: Python :: 3.9
Classifier: Programming Language :: Python :: 3.10
Classifier: Programming Language :: Python :: 3.11
Classifier: Programming Language :: Python :: 3.12
Classifier: Programming Language :: Python :: 3 :: Only
Classifier: License :: OSI Approved :: MIT License
Classifier: Operating System :: OS Independent
Requires-Python: >=3.8
License-File: LICENSE
Requires-Dist: pillow
Requires-Dist: pillow-heif
Requires-Dist: numpy
Provides-Extra: dev
Requires-Dist: check-manifest; extra == "dev"
Dynamic: author
Dynamic: author-email
Dynamic: classifier
Dynamic: description
Dynamic: description-content-type
Dynamic: home-page
Dynamic: keywords
Dynamic: license-file
Dynamic: project-url
Dynamic: provides-extra
Dynamic: requires-dist
Dynamic: requires-python
Dynamic: summary
